rustic_ai/llm_agent/__init__.py
rustic_ai/llm_agent/llm_agent.py
rustic_ai/llm_agent/llm_agent_conf.py
rustic_ai/llm_agent/llm_agent_helper.py
rustic_ai/llm_agent/llm_agent_utils.py
rustic_ai/llm_agent/memories/__init__.py
rustic_ai/llm_agent/memories/guild_state_memories_store.py
rustic_ai/llm_agent/memories/history_memories_store.py
rustic_ai/llm_agent/memories/memories_store.py
rustic_ai/llm_agent/memories/queue_memories_store.py
rustic_ai/llm_agent/memories/state_memories_store.py
rustic_ai/llm_agent/model.py
rustic_ai/llm_agent/plugins/__init__.py
rustic_ai/llm_agent/plugins/llm_call_wrapper.py
rustic_ai/llm_agent/plugins/prompt_generators.py
rustic_ai/llm_agent/plugins/request_preprocessor.py
rustic_ai/llm_agent/plugins/response_postprocessor.py
rustic_ai/llm_agent/tool_enabled_agent.py
rustic_ai/llm_agent/tools/__init__.py
rustic_ai/llm_agent/tools/tools_manager_plugin.py
rustic_ai/llm_agent/tools/tools_provider.py
rusticai_llm_agent-1.0.0.dist-info/METADATA
rusticai_llm_agent-1.0.0.dist-info/WHEEL
rusticai_llm_agent-1.0.0.dist-info/RECORD
